vlttng/__init__.py
vlttng/activate_template.py
vlttng/build_template.py
vlttng/conf_template.py
vlttng/install_template.py
vlttng/profile.py
vlttng/profiles/all-master.yml
vlttng/profiles/babeltrace-1.0.0-pre1.yml
vlttng/profiles/babeltrace-1.0.0-pre2.yml
vlttng/profiles/babeltrace-1.0.0-pre3.yml
vlttng/profiles/babeltrace-1.0.0-pre4.yml
vlttng/profiles/babeltrace-1.0.0-rc1.yml
vlttng/profiles/babeltrace-1.0.0-rc2.yml
vlttng/profiles/babeltrace-1.0.0-rc3.yml
vlttng/profiles/babeltrace-1.0.0-rc4.yml
vlttng/profiles/babeltrace-1.0.0-rc5.yml
vlttng/profiles/babeltrace-1.0.0-rc6.yml
vlttng/profiles/babeltrace-1.0.0.yml
vlttng/profiles/babeltrace-1.0.1.yml
vlttng/profiles/babeltrace-1.0.2.yml
vlttng/profiles/babeltrace-1.0.3.yml
vlttng/profiles/babeltrace-1.1.0.yml
vlttng/profiles/babeltrace-1.1.1.yml
vlttng/profiles/babeltrace-1.1.2.yml
vlttng/profiles/babeltrace-1.2.0-rc1.yml
vlttng/profiles/babeltrace-1.2.0-rc2.yml
vlttng/profiles/babeltrace-1.2.0.yml
vlttng/profiles/babeltrace-1.2.1.yml
vlttng/profiles/babeltrace-1.2.2.yml
vlttng/profiles/babeltrace-1.2.3.yml
vlttng/profiles/babeltrace-1.2.4.yml
vlttng/profiles/babeltrace-1.2.5.yml
vlttng/profiles/babeltrace-1.2.6.yml
vlttng/profiles/babeltrace-1.3.0.yml
vlttng/profiles/babeltrace-1.3.1.yml
vlttng/profiles/babeltrace-1.3.2.yml
vlttng/profiles/babeltrace-1.3.3.yml
vlttng/profiles/babeltrace-1.4.0-rc1.yml
vlttng/profiles/babeltrace-1.4.0.yml
vlttng/profiles/babeltrace-1.4.1.yml
vlttng/profiles/babeltrace-1.4.2.yml
vlttng/profiles/babeltrace-1.4.3.yml
vlttng/profiles/babeltrace-1.4.4.yml
vlttng/profiles/babeltrace-1.5.0-rc1.yml
vlttng/profiles/babeltrace-1.5.0.yml
vlttng/profiles/babeltrace-1.5.1.yml
vlttng/profiles/babeltrace-1.5.10.yml
vlttng/profiles/babeltrace-1.5.11.yml
vlttng/profiles/babeltrace-1.5.2.yml
vlttng/profiles/babeltrace-1.5.3.yml
vlttng/profiles/babeltrace-1.5.4.yml
vlttng/profiles/babeltrace-1.5.5.yml
vlttng/profiles/babeltrace-1.5.6.yml
vlttng/profiles/babeltrace-1.5.7.yml
vlttng-0.11.2.dist-info/LICENSE
vlttng-0.11.2.dist-info/METADATA
vlttng-0.11.2.dist-info/WHEEL
vlttng-0.11.2.dist-info/entry_points.txt
vlttng-0.11.2.dist-info/RECORD
