Metadata-Version: 2.1
Name: vlttng
Version: 0.11.2
Summary: Generator of LTTng virtual environment
Home-page: https://github.com/eepp/vlttng/
License: MIT
Keywords: lttng
Author: Philippe Proulx
Author-email: eeppeliteloop@gmail.com
Requires-Python: >=3.6,<4.0
Classifier: Development Status :: 4 - Beta
Classifier: Environment :: Console
Classifier: Intended Audience :: Developers
Classifier: Intended Audience :: System Administrators
Classifier: License :: OSI Approved :: MIT License
Classifier: Natural Language :: English
Classifier: Operating System :: POSIX :: Linux
Classifier: Programming Language :: Python :: 3
Classifier: Programming Language :: Python :: 3.6
Classifier: Programming Language :: Python :: 3.7
Classifier: Programming Language :: Python :: 3.8
Classifier: Programming Language :: Python :: 3.9
Classifier: Programming Language :: Python :: 3.10
Classifier: Programming Language :: Python :: 3.11
Classifier: Programming Language :: Python :: 3.12
Classifier: Programming Language :: Python :: 3 :: Only
Classifier: Topic :: Software Development :: Build Tools
Requires-Dist: pyyaml (>=6,<7)
Requires-Dist: setuptools
Requires-Dist: termcolor (>=1.1,<2.0)
Project-URL: Repository, https://github.com/eepp/vlttng/
